Workbook

Sheet Paramètres
A1: Simulateur de commissions — apporteurs d'affaires My Easy Auto
A2: Cellules JAUNES = à modifier. Tout le reste est calculé. Grille en vigueur au 1er septembre 2026 (MY EASY AUTO).
A4: Légende : jaune = hypothèse modifiable · bleu = valeur saisie · noir = formule
A6: Formule | B6: Prix HT / mois | C6: Heures Adhésion Service | D6: Prime de signature | E6: Prime de fidélité — supprimée (grille v1.2), laissée à 0 | F6: Bonus engagement 12 mois | G6: Chargé de mission / mois (heures × taux) | H6: Coût technique / mois
A7: ESSENTIEL | B7: 79 | C7: 0 | D7: 130 | E7: 0 | F7: 40 | G7: =C7*$G$14 -> 0 | H7: =$G$15 -> 25
A8: ADHÉSION SERVICE PLUS | B8: 490 | C8: 10 | D8: 415 | E8: 0 | F8: 85 | G8: =C8*$G$14 -> 170 | H8: =$G$15 -> 25
A9: ADHÉSION SERVICE PREMIUM | B9: 860 | C9: 20 | D9: 730 | E9: 0 | F9: 85 | G9: =C9*$G$14 -> 340 | H9: =$G$15 -> 25
A10: ADHÉSION SERVICE ULTIMATE | B10: 1570 | C10: 40 | D10: 1335 | E10: 0 | F10: 85 | G10: =C10*$G$14 -> 680 | H10: =$G$15 -> 25
A12: Hypothèses générales
A13: Taux de conservation des garages à M6 | G13: 0.85
A14: Taux horaire versé au chargé de mission (€ HT / heure de forfait) | G14: 17
A15: Coût technique par garage et par mois (hébergement, IA, emails) | G15: 25
A16: Part des devis signés avec engagement 12 mois | G16: 0.6
A17: Délai avant paiement de la prime (mois après signature) — v1.3 : 1 avec engagement 12 mois, 3 sans engagement | G17: 1
A18: Délai avant paiement de la prime de fidélité (mois après signature) | G18: 6
A20: Bonus de volume trimestriel (hors ESSENTIEL, non cumulables)
A21: Palier | B21: Contrats dans le trimestre | C21: Bonus
A22: Palier 1 | B22: 5 | C22: 255
A23: Palier 2 | B23: 10 | C23: 680
A25: Source des prix et du taux horaire : NOTE-STRATEGIE-TARIFAIRE et MYEASYAUTO_modele_rentabilite.xlsx (docs/pack-commercial). Commissions : grille apporteurs v1.3, en vigueur au 1er septembre 2026 (une prime unique par garage ; versée dès la 1re mensualité si engagement 12 mois, à la 3e sinon ; reprise si arrêt avant 3 mensualités).

Sheet Simulation commercial
A1: Ce que gagne le commercial selon son rythme
A2: Saisissez vos signatures mensuelles par formule (jaune). Grille v1.3 : une prime par garage signé, versée dès la 1re mensualité encaissée avec engagement 12 mois (3e mensualité sans engagement) ; le délai retenu est celui de l'onglet Paramètres (G17).
A4: Signatures par mois | B4: ESSENTIEL | C4: ADHÉSION SERVICE PLUS | D4: ADHÉSION SERVICE PREMIUM | E4: ADHÉSION SERVICE ULTIMATE | F4: Total / mois
A5: Nombre de contrats signés / mois | B5: 1 | C5: 2 | D5: 1 | E5: 0 | F5: =SUM(B5:E5) -> 4
A7: Commissions générées par UN mois de signatures
A8: Poste | B8: ESSENTIEL | C8: ADHÉSION SERVICE PLUS | D8: ADHÉSION SERVICE PREMIUM | E8: ADHÉSION SERVICE ULTIMATE | F8: Total
A9: Primes de signature | B9: =B$5*Paramètres!$D$7 -> 130 | C9: =C$5*Paramètres!$D$8 -> 830 | D9: =D$5*Paramètres!$D$9 -> 730 | E9: =E$5*Paramètres!$D$10 -> 0 | F9: =SUM(B9:E9) -> 1690
A10: Bonus engagement 12 mois (× part engagée) | B10: =B$5*Paramètres!$F$7*Paramètres!$G$16 -> 24 | C10: =C$5*Paramètres!$F$8*Paramètres!$G$16 -> 102 | D10: =D$5*Paramètres!$F$9*Paramètres!$G$16 -> 51 | E10: =E$5*Paramètres!$F$10*Paramètres!$G$16 -> 0 | F10: =SUM(B10:E10) -> 177
A11: Primes de fidélité — supprimées (grille v1.2), à 0 | B11: =B$5*Paramètres!$E$7*Paramètres!$G$13 -> 0 | C11: =C$5*Paramètres!$E$8*Paramètres!$G$13 -> 0 | D11: =D$5*Paramètres!$E$9*Paramètres!$G$13 -> 0 | E11: =E$5*Paramètres!$E$10*Paramètres!$G$13 -> 0 | F11: =SUM(B11:E11) -> 0
A12: Total généré par un mois de signatures | B12: =SUM(B9:B11) -> 154 | C12: =SUM(C9:C11) -> 932 | D12: =SUM(D9:D11) -> 781 | E12: =SUM(E9:E11) -> 0 | F12: =SUM(F9:F11) -> 1867
A14: Trésorerie du commercial sur 24 mois (même rythme chaque mois)
A15: Les primes de signature arrivent avec le décalage indiqué dans Paramètres (G17), la fidélité avec G18. Le bonus de volume est calculé par trimestre civil sur les contrats hors Essentiel.
A16: Mois | B16: Signatures | C16: Primes de signature + bonus engagement perçus | D16: Primes de fidélité (supprimées, à 0) | E16: Bonus de volume | F16: Total perçu | G16: Cumul
A17: 1 | B17: =$F$5 -> 4 | C17: =IF(A17>Paramètres!$G$17,$F$9+$F$10,0) -> 0 | D17: =IF(A17>Paramètres!$G$18,$F$11,0) -> 0 | E17: =IF(MOD(A17,3)=0,IF(3*($C$5+$D$5+$E$5)>=Paramètres!$B$23,Paramètres!$C$23,IF(3*($C$5+$D$5+$E$5)>=Paramètres!$B$22,Paramètres!$C$22,0)),0) -> 0 | F17: =C17+D17+E17 -> 0 | G17: =SUM($F$17:F17) -> 0
A18: 2 | B18: =$F$5 -> 4 | C18: =IF(A18>Paramètres!$G$17,$F$9+$F$10,0) -> 0 | D18: =IF(A18>Paramètres!$G$18,$F$11,0) -> 0 | E18: =IF(MOD(A18,3)=0,IF(3*($C$5+$D$5+$E$5)>=Paramètres!$B$23,Paramètres!$C$23,IF(3*($C$5+$D$5+$E$5)>=Paramètres!$B$22,Paramètres!$C$22,0)),0) -> 0 | F18: =C18+D18+E18 -> 0 | G18: =SUM($F$17:F18) -> 0
A19: 3 | B19: =$F$5 -> 4 | C19: =IF(A19>Paramètres!$G$17,$F$9+$F$10,0) -> 1867 | D19: =IF(A19>Paramètres!$G$18,$F$11,0) -> 0 | E19: =IF(MOD(A19,3)=0,IF(3*($C$5+$D$5+$E$5)>=Paramètres!$B$23,Paramètres!$C$23,IF(3*($C$5+$D$5+$E$5)>=Paramètres!$B$22,Paramètres!$C$22,0)),0) -> 255 | F19: =C19+D19+E19 -> 2122 | G19: =SUM($F$17:F19) -> 2122
A20: 4 | B20: =$F$5 -> 4 | C20: =IF(A20>Paramètres!$G$17,$F$9+$F$10,0) -> 1867 | D20: =IF(A20>Paramètres!$G$18,$F$11,0) -> 0 | E20: =IF(MOD(A20,3)=0,IF(3*($C$5+$D$5+$E$5)>=Paramètres!$B$23,Paramètres!$C$23,IF(3*($C$5+$D$5+$E$5)>=Paramètres!$B$22,Paramètres!$C$22,0)),0) -> 0 | F20: =C20+D20+E20 -> 1867 | G20: =SUM($F$17:F20) -> 3989
A21: 5 | B21: =$F$5 -> 4 | C21: =IF(A21>Paramètres!$G$17,$F$9+$F$10,0) -> 1867 | D21: =IF(A21>Paramètres!$G$18,$F$11,0) -> 0 | E21: =IF(MOD(A21,3)=0,IF(3*($C$5+$D$5+$E$5)>=Paramètres!$B$23,Paramètres!$C$23,IF(3*($C$5+$D$5+$E$5)>=Paramètres!$B$22,Paramètres!$C$22,0)),0) -> 0 | F21: =C21+D21+E21 -> 1867 | G21: =SUM($F$17:F21) -> 5856
A22: 6 | B22: =$F$5 -> 4 | C22: =IF(A22>Paramètres!$G$17,$F$9+$F$10,0) -> 1867 | D22: =IF(A22>Paramètres!$G$18,$F$11,0) -> 0 | E22: =IF(MOD(A22,3)=0,IF(3*($C$5+$D$5+$E$5)>=Paramètres!$B$23,Paramètres!$C$23,IF(3*($C$5+$D$5+$E$5)>=Paramètres!$B$22,Paramètres!$C$22,0)),0) -> 255 | F22: =C22+D22+E22 -> 2122 | G22: =SUM($F$17:F22) -> 7978
A23: 7 | B23: =$F$5 -> 4 | C23: =IF(A23>Paramètres!$G$17,$F$9+$F$10,0) -> 1867 | D23: =IF(A23>Paramètres!$G$18,$F$11,0) -> 0 | E23: =IF(MOD(A23,3)=0,IF(3*($C$5+$D$5+$E$5)>=Paramètres!$B$23,Paramètres!$C$23,IF(3*($C$5+$D$5+$E$5)>=Paramètres!$B$22,Paramètres!$C$22,0)),0) -> 0 | F23: =C23+D23+E23 -> 1867 | G23: =SUM($F$17:F23) -> 9845
A24: 8 | B24: =$F$5 -> 4 | C24: =IF(A24>Paramètres!$G$17,$F$9+$F$10,0) -> 1867 | D24: =IF(A24>Paramètres!$G$18,$F$11,0) -> 0 | E24: =IF(MOD(A24,3)=0,IF(3*($C$5+$D$5+$E$5)>=Paramètres!$B$23,Paramètres!$C$23,IF(3*($C$5+$D$5+$E$5)>=Paramètres!$B$22,Paramètres!$C$22,0)),0) -> 0 | F24: =C24+D24+E24 -> 1867 | G24: =SUM($F$17:F24) -> 11712
A25: 9 | B25: =$F$5 -> 4 | C25: =IF(A25>Paramètres!$G$17,$F$9+$F$10,0) -> 1867 | D25: =IF(A25>Paramètres!$G$18,$F$11,0) -> 0 | E25: =IF(MOD(A25,3)=0,IF(3*($C$5+$D$5+$E$5)>=Paramètres!$B$23,Paramètres!$C$23,IF(3*($C$5+$D$5+$E$5)>=Paramètres!$B$22,Paramètres!$C$22,0)),0) -> 255 | F25: =C25+D25+E25 -> 2122 | G25: =SUM($F$17:F25) -> 13834
A26: 10 | B26: =$F$5 -> 4 | C26: =IF(A26>Paramètres!$G$17,$F$9+$F$10,0) -> 1867 | D26: =IF(A26>Paramètres!$G$18,$F$11,0) -> 0 | E26: =IF(MOD(A26,3)=0,IF(3*($C$5+$D$5+$E$5)>=Paramètres!$B$23,Paramètres!$C$23,IF(3*($C$5+$D$5+$E$5)>=Paramètres!$B$22,Paramètres!$C$22,0)),0) -> 0 | F26: =C26+D26+E26 -> 1867 | G26: =SUM($F$17:F26) -> 15701
A27: 11 | B27: =$F$5 -> 4 | C27: =IF(A27>Paramètres!$G$17,$F$9+$F$10,0) -> 1867 | D27: =IF(A27>Paramètres!$G$18,$F$11,0) -> 0 | E27: =IF(MOD(A27,3)=0,IF(3*($C$5+$D$5+$E$5)>=Paramètres!$B$23,Paramètres!$C$23,IF(3*($C$5+$D$5+$E$5)>=Paramètres!$B$22,Paramètres!$C$22,0)),0) -> 0 | F27: =C27+D27+E27 -> 1867 | G27: =SUM($F$17:F27) -> 17568
A28: 12 | B28: =$F$5 -> 4 | C28: =IF(A28>Paramètres!$G$17,$F$9+$F$10,0) -> 1867 | D28: =IF(A28>Paramètres!$G$18,$F$11,0) -> 0 | E28: =IF(MOD(A28,3)=0,IF(3*($C$5+$D$5+$E$5)>=Paramètres!$B$23,Paramètres!$C$23,IF(3*($C$5+$D$5+$E$5)>=Paramètres!$B$22,Paramètres!$C$22,0)),0) -> 255 | F28: =C28+D28+E28 -> 2122 | G28: =SUM($F$17:F28) -> 19690
... A40: 24 | B40: =$F$5 -> 4 | C40: =IF(A40>Paramètres!$G$17,$F$9+$F$10,0) -> 1867 | D40: =IF(A40>Paramètres!$G$18,$F$11,0) -> 0 | E40: =IF(MOD(A40,3)=0,IF(3*($C$5+$D$5+$E$5)>=Paramètres!$B$23,Paramètres!$C$23,IF(3*($C$5+$D$5+$E$5)>=Paramètres!$B$22,Paramètres!$C$22,0)),0) -> 255 | F40: =C40+D40+E40 -> 2122 | G40: =SUM($F$17:F40) -> 43114
A41: Perçu sur les 12 premiers mois | F41: =SUM(F17:F28) -> 19690
A42: Perçu sur la 2e année (régime de croisière) | F42: =SUM(F29:F40) -> 23424
A43: Revenu mensuel moyen en croisière | F43: =F42/12 -> 1952

Sheet Rentabilité MY EASY AUTO
A1: Ce que rapporte un garage à MY EASY AUTO, commissions comprises
A2: Par formule, sur la première année (avec commission) puis en année 2 (sans commission). Toutes les hypothèses viennent de l'onglet Paramètres.
A4: Année 1 — par garage | B4: ESSENTIEL | C4: ADHÉSION SERVICE PLUS | D4: ADHÉSION SERVICE PREMIUM | E4: ADHÉSION SERVICE ULTIMATE
A5: Chiffre d'affaires HT (12 mois) | B5: =Paramètres!B7*12 -> 948 | C5: =Paramètres!B8*12 -> 5880 | D5: =Paramètres!B9*12 -> 10320 | E5: =Paramètres!B10*12 -> 18840
A6: Chargé de mission (heures × taux horaire) | B6: =-Paramètres!G7*12 -> 0 | C6: =-Paramètres!G8*12 -> -2040 | D6: =-Paramètres!G9*12 -> -4080 | E6: =-Paramètres!G10*12 -> -8160
A7: Coûts techniques | B7: =-Paramètres!H7*12 -> -300 | C7: =-Paramètres!H8*12 -> -300 | D7: =-Paramètres!H9*12 -> -300 | E7: =-Paramètres!H10*12 -> -300
A8: Commission apporteur : signature + bonus engagement (× part engagée) | B8: =-(Paramètres!D7+Paramètres!F7*Paramètres!$G$16) -> -154 | C8: =-(Paramètres!D8+Paramètres!F8*Paramètres!$G$16) -> -466 | D8: =-(Paramètres!D9+Paramètres!F9*Paramètres!$G$16) -> -781 | E8: =-(Paramètres!D10+Paramètres!F10*Paramètres!$G$16) -> -1386
A9: Commission apporteur : fidélité — supprimée, à 0 | B9: =-Paramètres!E7*Paramètres!$G$13 -> 0 | C9: =-Paramètres!E8*Paramètres!$G$13 -> 0 | D9: =-Paramètres!E9*Paramètres!$G$13 -> 0 | E9: =-Paramètres!E10*Paramètres!$G$13 -> 0
A10: Marge brute année 1 (avant coûts fixes et rémunération) | B10: =SUM(B5:B9) -> 494 | C10: =SUM(C5:C9) -> 3074 | D10: =SUM(D5:D9) -> 5159 | E10: =SUM(E5:E9) -> 8994
A11: Marge année 1 en % du CA | B11: =IF(B5=0,0,B10/B5) -> 0.52109705 | C11: =IF(C5=0,0,C10/C5) -> 0.52278912 | D11: =IF(D5=0,0,D10/D5) -> 0.4999031 | E11: =IF(E5=0,0,E10/E5) -> 0.47738854
A12: Part de la marge reversée au commercial | B12: =IF(B10-B8-B9=0,0,-(B8+B9)/(B10-B8-B9)) -> 0.23765432 | C12: =IF(C10-C8-C9=0,0,-(C8+C9)/(C10-C8-C9)) -> 0.13163842 | D12: =IF(D10-D8-D9=0,0,-(D8+D9)/(D10-D8-D9)) -> 0.13148148 | E12: =IF(E10-E8-E9=0,0,-(E8+E9)/(E10-E8-E9)) -> 0.13352601
A14: Année 2 et suivantes — par garage | B14: ESSENTIEL | C14: ADHÉSION SERVICE PLUS | D14: ADHÉSION SERVICE PREMIUM | E14: ADHÉSION SERVICE ULTIMATE
A15: Chiffre d'affaires HT (12 mois) | B15: =Paramètres!B7*12 -> 948 | C15: =Paramètres!B8*12 -> 5880 | D15: =Paramètres!B9*12 -> 10320 | E15: =Paramètres!B10*12 -> 18840
A16: Chargé de mission + coûts techniques | B16: =-(Paramètres!G7+Paramètres!H7)*12 -> -300 | C16: =-(Paramètres!G8+Paramètres!H8)*12 -> -2340 | D16: =-(Paramètres!G9+Paramètres!H9)*12 -> -4380 | E16: =-(Paramètres!G10+Paramètres!H10)*12 -> -8460
A17: Marge brute année 2 (aucune commission) | B17: =B15+B16 -> 648 | C17: =C15+C16 -> 3540 | D17: =D15+D16 -> 5940 | E17: =E15+E16 -> 10380
A19: Vue portefeuille : avec le rythme saisi dans « Simulation commercial » pendant 12 mois
A20: Poste | B20: ESSENTIEL | C20: ADHÉSION SERVICE PLUS | D20: ADHÉSION SERVICE PREMIUM | E20: ADHÉSION SERVICE ULTIMATE | F20: Total
A21: Garages signés sur 12 mois | B21: ='Simulation commercial'!B5*12 -> 12 | C21: ='Simulation commercial'!C5*12 -> 24 | D21: ='Simulation commercial'!D5*12 -> 12 | E21: ='Simulation commercial'!E5*12 -> 0 | F21: =SUM(B21:E21) -> 48
A22: Marge brute année 1 de ces garages (commissions déduites) | B22: =B21*B10 -> 5928 | C22: =C21*C10 -> 73776 | D22: =D21*D10 -> 61908 | E22: =E21*E10 -> 0 | F22: =SUM(B22:E22) -> 141612
A23: Marge brute récurrente en année 2 (× taux de conservation) | B23: =B21*B17*Paramètres!$G$13 -> 6609.6 | C23: =C21*C17*Paramètres!$G$13 -> 72216 | D23: =D21*D17*Paramètres!$G$13 -> 60588 | E23: =E21*E17*Paramètres!$G$13 -> 0 | F23: =SUM(B23:E23) -> 139413.6
A25: Lecture : la commission représente environ 13 % de la marge brute de la première année sur les formules Adhésion Service, et rien ensuite. Les coûts fixes d'MY EASY AUTO (~270 € / mois, cf. note stratégique) et la rémunération du dirigeant ne sont pas déduits ici.

Sheet Suivi prospects
A1: Suivi des prospects — à envoyer chaque vendredi à contact@myeasyauto.fr
A2: Une ligne par garage. Les colonnes « Étape » et « Formule » sont des listes déroulantes. La ligne 5 est un exemple à remplacer.
A4: Date 1er contact | B4: Garage | C4: Ville | D4: Contact (nom) | E4: Téléphone | F4: Email | G4: Dossiers sinistre / mois | H4: Qui fait l'administratif ? | I4: En attente chez les assurances (€) | J4: Étape | K4: Date déclaration lead | L4: Date démo | M4: Formule visée | N4: Engagement 12 mois | O4: Date signature | P4: Prochaine action | Q4: Commentaires | S4: Tableau de bord
A5: 2026-09-02 | B5: Carrosserie Exemple | C5: Nanterre | D5: M. Martin | E5: 06 00 00 00 00 | F5: contact@carrosserie-exemple.fr | G5: 25 | H5: Le patron, le soir | I5: 14000 | J5: Démo planifiée | K5: 2026-09-03 | L5: 2026-09-10 | M5: ADHÉSION SERVICE PREMIUM | N5: Oui | P5: Rappeler après la démo | Q5: Personne chargée de l'administratif partie en juin, 3 factures AXA > 90 jours | S5: Garages contactés | T5: =COUNTA(B5:B200) -> 1
S6: Prospects qualifiés (au-delà de « Contacté ») | T6: =COUNTIFS(J5:J200,"<>À contacter",J5:J200,"<>Contacté",B5:B200,"<>") -> 1
S7: Leads déclarés | T7: =COUNTA(K5:K200) -> 1
S8: Démos planifiées ou faites | T8: =COUNTA(L5:L200) -> 1
S9: Signatures | T9: =COUNTIF(J5:J200,"Signé") -> 0
S10: Taux de signature / contactés | T10: =IF(T5=0,0,T9/T5) -> 0
