Workbook

Sheet Hypothèses
B2: HYPOTHÈSES DU MODÈLE — à ajuster (cellules jaunes)
B4: TARIFS DE VENTE AUX GARAGES (HT)
B5: Abonnement appli My Easy Auto seule (€ / mois) | C5: 79 | D5: Marché des logiciels garage : 29–59 € (AutoProGestion) ; l'IA d'extraction justifie un positionnement supérieur.
B6: Taux horaire secrétariat — forfait 10 h (€ / h) | C6: 41.1 | D6: Dégressif : plus le garage s'engage, moins l'heure coûte.
B7: Taux horaire secrétariat — forfait 20 h (€ / h) | C7: 39.05 | D7: Marché secrétaire indépendante : 30–50 € / h (spécialisation sinistres = haut de fourchette).
B8: Taux horaire secrétariat — forfait 40 h (€ / h) | C8: 37.275
B9: Heure hors forfait / dépassement (€ / h) | C9: 45 | D9: Aligné sur le haut du marché : incite à prendre un forfait supérieur.
B10: Mise en service + formation (€, une fois) | C10: 290 | D10: Offerte si engagement 12 mois (levier de négociation).
B11: RÉTROCESSION COLLABORATEUR (auto-entrepreneur)
B12: Part du CA secrétariat reversée au collaborateur | C12: 0.65 | D12: 65 % : taux attractif vs plateformes (50–60 %) tout en préservant la marge.
B13: Cotisations sociales auto-entrepreneur (indicatif) | C13: 0.262 | D13: Prestations de services BNC 2026 ≈ 26,2 % — à vérifier selon le statut réel du collaborateur.
B14: COÛTS IDEA FORMA PAR GARAGE ACTIF (€ / mois)
B15: Hébergement + base de données (Vercel / Supabase, quote-part) | C15: 8 | D15: Forfaits Pro ≈ 20 $ + 25 $ / mois répartis sur le parc de garages.
B16: API IA — extraction des rapports (quote-part) | C16: 12 | D16: Dépend du quota d'analyses / garage / mois (voir Consommation IA dans l'appli).
B17: Outils divers (mail, signature, sauvegardes…) | C17: 5
B18: COÛTS FIXES IDEA FORMA (€ / mois, tout le parc)
B19: Comptabilité, assurance RC pro, bancaire | C19: 120 | D19: RC pro indispensable (traitement de données clients des garages).
B20: Commercial / déplacements / impression plaquettes | C20: 150
B21: ACTIVITÉ MOYENNE
B22: Heures moyennes réellement consommées / garage / mois | C22: 20 | D22: Base forfait CONFORT — sert aux simulations.
B24: Légende : cellules JAUNES = hypothèses à ajuster (texte bleu). Le reste du classeur se recalcule automatiquement.
B25: Sources marché : plateya.fr (35–50 €/h, forfaits 500–800 €/mois), kmfservices.fr (20–50 €/h), autoprogestion.fr (logiciel 29–59 €/mois).

Sheet Grille tarifaire
B2: GRILLE TARIFAIRE CLIENT — € HT / mois
B4: Formule | C4: ESSENTIEL | D4: STARTER | E4: CONFORT | F4: SÉRÉNITÉ
B5: Heures de secrétariat incluses | C5: 0 | D5: 10 | E5: 20 | F5: 40
B6: Appli My Easy Auto incluse | C6: Oui | D6: Oui | E6: Oui | F6: Oui
B7: Taux horaire appliqué (€/h) | C7: — | D7: =Hypothèses!C6 -> 41.1 | E7: =Hypothèses!C7 -> 39.05 | F7: =Hypothèses!C8 -> 37.275
B8: Prix mensuel HT | C8: =Hypothèses!C5 -> 79 | D8: =Hypothèses!C5+D5*D7 -> 490 | E8: =Hypothèses!C5+E5*E7 -> 860 | F8: =Hypothèses!C5+F5*F7 -> 1570
B9: Heure supplémentaire (€/h HT) | C9: =Hypothèses!C9 -> 45 | D9: =Hypothèses!C9 -> 45 | E9: =Hypothèses!C9 -> 45 | F9: =Hypothèses!C9 -> 45
B10: Mise en service (une fois, HT) | C10: =Hypothèses!C10 -> 290 | D10: =Hypothèses!C10 -> 290 | E10: =Hypothèses!C10 -> 290 | F10: =Hypothèses!C10 -> 290
B12: Mise en service offerte pour tout engagement de 12 mois. TVA en sus selon le régime fiscal d'IDEA FORMA.

Sheet Rentabilité
B2: RENTABILITÉ IDEA FORMA — PAR GARAGE ET PAR PARC
B4: Par garage / mois | C4: STARTER | D4: CONFORT | E4: SÉRÉNITÉ | F4: Appli seule
B5: Chiffre d'affaires HT | C5: ='Grille tarifaire'!D8 -> 490 | D5: ='Grille tarifaire'!E8 -> 860 | E5: ='Grille tarifaire'!F8 -> 1570 | F5: =Hypothèses!C5 -> 79
B6: dont part secrétariat | C6: =C5-Hypothèses!$C$5 -> 411 | D6: =D5-Hypothèses!$C$5 -> 781 | E6: =E5-Hypothèses!$C$5 -> 1491 | F6: 0
B7: Rétrocession collaborateur | C7: =-C6*Hypothèses!$C$12 -> -267.15 | D7: =-D6*Hypothèses!$C$12 -> -507.65 | E7: =-E6*Hypothèses!$C$12 -> -969.15 | F7: 0
B8: Coûts techniques (hébergement + IA + outils) | C8: =-(Hypothèses!$C$15+Hypothèses!$C$16+Hypothèses!$C$17) -> -25 | D8: =-(Hypothèses!$C$15+Hypothèses!$C$16+Hypothèses!$C$17) -> -25 | E8: =-(Hypothèses!$C$15+Hypothèses!$C$16+Hypothèses!$C$17) -> -25 | F8: =-(Hypothèses!$C$15+Hypothèses!$C$16+Hypothèses!$C$17) -> -25
B9: MARGE BRUTE / garage / mois | C9: =C5+C7+C8 -> 197.85 | D9: =D5+D7+D8 -> 327.35 | E9: =E5+E7+E8 -> 575.85 | F9: =F5+F7+F8 -> 54
B10: Marge en % du CA | C10: =C9/C5 -> 0.40377551 | D10: =D9/D5 -> 0.38063953 | E10: =E9/E5 -> 0.36678344 | F10: =F9/F5 -> 0.6835443
B12: SEUIL DE RENTABILITÉ (couverture des coûts fixes mensuels)
B13: Coûts fixes mensuels IDEA FORMA | C13: =Hypothèses!C19+Hypothèses!C20 -> 270
B14: Nombre de garages CONFORT pour couvrir les coûts fixes | C14: =ROUNDUP(C13/D9,0) -> 1
B16: PROJECTION — PARC DE GARAGES (répartition : 30 % STARTER, 50 % CONFORT, 20 % SÉRÉNITÉ)
B17: Nb de garages | C17: CA mensuel HT | D17: Marge brute | E17: − Coûts fixes | F17: Résultat / mois
B18: 2 | C18: =B18*(0.3*'Grille tarifaire'!$D$8+0.5*'Grille tarifaire'!$E$8+0.2*'Grille tarifaire'!$F$8) -> 1782 | D18: =B18*(0.3*$C$9+0.5*$D$9+0.2*$E$9) -> 676.4 | E18: =-($C$13) -> -270 | F18: =D18+E18 -> 406.4
B19: 5 | C19: =B19*(0.3*'Grille tarifaire'!$D$8+0.5*'Grille tarifaire'!$E$8+0.2*'Grille tarifaire'!$F$8) -> 4455 | D19: =B19*(0.3*$C$9+0.5*$D$9+0.2*$E$9) -> 1691 | E19: =-($C$13) -> -270 | F19: =D19+E19 -> 1421
B20: 10 | C20: =B20*(0.3*'Grille tarifaire'!$D$8+0.5*'Grille tarifaire'!$E$8+0.2*'Grille tarifaire'!$F$8) -> 8910 | D20: =B20*(0.3*$C$9+0.5*$D$9+0.2*$E$9) -> 3382 | E20: =-($C$13) -> -270 | F20: =D20+E20 -> 3112
B21: 20 | C21: =B21*(0.3*'Grille tarifaire'!$D$8+0.5*'Grille tarifaire'!$E$8+0.2*'Grille tarifaire'!$F$8) -> 17820 | D21: =B21*(0.3*$C$9+0.5*$D$9+0.2*$E$9) -> 6764 | E21: =-($C$13) -> -270 | F21: =D21+E21 -> 6494
B22: 30 | C22: =B22*(0.3*'Grille tarifaire'!$D$8+0.5*'Grille tarifaire'!$E$8+0.2*'Grille tarifaire'!$F$8) -> 26730 | D22: =B22*(0.3*$C$9+0.5*$D$9+0.2*$E$9) -> 10146 | E22: =-($C$13) -> -270 | F22: =D22+E22 -> 9876
B24: Répartition du parc modifiable dans les formules de la colonne CA. Résultat avant impôt et rémunération du dirigeant.

Sheet Collaborateur
B2: REVENUS DU COLLABORATEUR (auto-entrepreneur)
B4: Taux horaire moyen rétrocédé (base forfait CONFORT) | C4: =Hypothèses!C7*Hypothèses!C12 -> 25.3825
B6: Garages suivis | C6: Heures / mois | D6: CA mensuel | E6: Cotisations | F6: Net avant IR
B7: 1 | C7: =B7*Hypothèses!$C$22 -> 20 | D7: =C7*$C$4 -> 507.65 | E7: =-D7*Hypothèses!$C$13 -> -133.0043 | F7: =D7+E7 -> 374.6457
B8: 2 | C8: =B8*Hypothèses!$C$22 -> 40 | D8: =C8*$C$4 -> 1015.3 | E8: =-D8*Hypothèses!$C$13 -> -266.0086 | F8: =D8+E8 -> 749.2914
B9: 3 | C9: =B9*Hypothèses!$C$22 -> 60 | D9: =C9*$C$4 -> 1522.95 | E9: =-D9*Hypothèses!$C$13 -> -399.0129 | F9: =D9+E9 -> 1123.9371
B10: 5 | C10: =B10*Hypothèses!$C$22 -> 100 | D10: =C10*$C$4 -> 2538.25 | E10: =-D10*Hypothèses!$C$13 -> -665.0215 | F10: =D10+E10 -> 1873.2285
B11: 7 | C11: =B11*Hypothèses!$C$22 -> 140 | D11: =C11*$C$4 -> 3553.55 | E11: =-D11*Hypothèses!$C$13 -> -931.0301 | F11: =D11+E11 -> 2622.5199
B13: Un collaborateur à 7 garages (≈ 140 h/mois) dégage un revenu comparable à un temps plein salarié, sans trajet.
B14: Cotisations : taux indicatif micro-entrepreneur, à vérifier selon l'activité déclarée (URSSAF). Hors impôt sur le revenu / VFL.
